pybetterloader/Loader.py
pybetterloader/__init__.py
pybetterloader-1.0.1.dist-info/LICENCE
pybetterloader-1.0.1.dist-info/METADATA
pybetterloader-1.0.1.dist-info/WHEEL
pybetterloader-1.0.1.dist-info/top_level.txt
pybetterloader-1.0.1.dist-info/RECORD
